<?xml version="1.0" encoding="utf-8"?>
	<annotation>
		<folder>driving_annotation_dataset</folder>
		<filename>000000039811.jpg</filename>
		<size>
			<width>640</width>
			<height>480</height>
			<depth>3</depth>
		</size>
		<object>
			<name>person</name>
			<pose>Unspecified</pose>
			<truncated>0</truncated>
			<difficult>0</difficult>
			<bndbox>
				<xmin>212</xmin>
				<ymin>171</ymin>
				<xmax>258</xmax>
				<ymax>214</ymax>
			</bndbox>
		</object>
		<object>
			<name>person</name>
			<pose>Unspecified</pose>
			<truncated>0</truncated>
			<difficult>0</difficult>
			<bndbox>
				<xmin>472</xmin>
				<ymin>198</ymin>
				<xmax>486</xmax>
				<ymax>234</ymax>
			</bndbox>
		</object>
		<object>
			<name>person</name>
			<pose>Unspecified</pose>
			<truncated>0</truncated>
			<difficult>0</difficult>
			<bndbox>
				<xmin>125</xmin>
				<ymin>212</ymin>
				<xmax>137</xmax>
				<ymax>238</ymax>
			</bndbox>
		</object>
	</annotation>
