<?xml version="1.0" encoding="utf-8"?>
	<annotation>
		<folder>driving_annotation_dataset</folder>
		<filename>000000066381.jpg</filename>
		<size>
			<width>640</width>
			<height>268</height>
			<depth>3</depth>
		</size>
		<object>
			<name>person</name>
			<pose>Unspecified</pose>
			<truncated>0</truncated>
			<difficult>0</difficult>
			<bndbox>
				<xmin>456</xmin>
				<ymin>12</ymin>
				<xmax>641</xmax>
				<ymax>269</ymax>
			</bndbox>
		</object>
		<object>
			<name>person</name>
			<pose>Unspecified</pose>
			<truncated>0</truncated>
			<difficult>0</difficult>
			<bndbox>
				<xmin>37</xmin>
				<ymin>84</ymin>
				<xmax>200</xmax>
				<ymax>264</ymax>
			</bndbox>
		</object>
	</annotation>
