<?xml version="1.0" encoding="utf-8"?>
	<annotation>
		<folder>driving_annotation_dataset</folder>
		<filename>000000088388.jpg</filename>
		<size>
			<width>640</width>
			<height>419</height>
			<depth>3</depth>
		</size>
		<object>
			<name>person</name>
			<pose>Unspecified</pose>
			<truncated>0</truncated>
			<difficult>0</difficult>
			<bndbox>
				<xmin>198</xmin>
				<ymin>96</ymin>
				<xmax>364</xmax>
				<ymax>400</ymax>
			</bndbox>
		</object>
		<object>
			<name>person</name>
			<pose>Unspecified</pose>
			<truncated>0</truncated>
			<difficult>0</difficult>
			<bndbox>
				<xmin>432</xmin>
				<ymin>251</ymin>
				<xmax>604</xmax>
				<ymax>420</ymax>
			</bndbox>
		</object>
		<object>
			<name>person</name>
			<pose>Unspecified</pose>
			<truncated>0</truncated>
			<difficult>0</difficult>
			<bndbox>
				<xmin>514</xmin>
				<ymin>225</ymin>
				<xmax>612</xmax>
				<ymax>336</ymax>
			</bndbox>
		</object>
	</annotation>
